excel_merger/__init__.py
excel_merger/cli.py
excel_merger/core.py
excel_merger/version.py
excel_merger-0.1.0.dist-info/licenses/LICENSE
excel_merger-0.1.0.dist-info/METADATA
excel_merger-0.1.0.dist-info/WHEEL
excel_merger-0.1.0.dist-info/entry_points.txt
excel_merger-0.1.0.dist-info/top_level.txt
excel_merger-0.1.0.dist-info/RECORD
