Metadata-Version: 2.4
Name: excel-merger
Version: 0.1.0
Summary: 一个强大的 Excel 文件合并工具，支持 CLI 和 Python API
Author-email: Your Name <your.email@example.com>
Project-URL: Homepage, https://github.com/yourusername/excel-merger
Project-URL: Repository, https://github.com/yourusername/excel-merger
Keywords: excel,merge,cli,pandas,typer,rich
Classifier: Development Status :: 4 - Beta
Classifier: Intended Audience :: Developers
Classifier: License :: OSI Approved :: MIT License
Classifier: Programming Language :: Python :: 3
Classifier: Programming Language :: Python :: 3.8
Classifier: Programming Language :: Python :: 3.9
Classifier: Programming Language :: Python :: 3.10
Classifier: Programming Language :: Python :: 3.11
Requires-Python: >=3.8
License-File: LICENSE
Requires-Dist: pandas>=1.5.0
Requires-Dist: openpyxl>=3.0.0
Requires-Dist: typer>=0.9.0
Requires-Dist: rich>=13.0.0
Provides-Extra: dev
Requires-Dist: pytest>=7.0.0; extra == "dev"
Requires-Dist: black>=22.0.0; extra == "dev"
Requires-Dist: flake8>=4.0.0; extra == "dev"
Dynamic: license-file
